{
    "Categories": "Qt;KDE;",
    "KPlugin": {
        "Description": "Configure general Konqueror behavior",
        "Description[ca]": "Configura el comportament general del Konqueror",
        "Description[es]": "Configurar el comportamiento general de Konqueror",
        "Description[eu]": "Konfiguratu «Konqueror»ren jokabide orokorra",
        "Description[nl]": "Algemeen gedrag van Konqueror instellen",
        "Description[sv]": "Anpassa Konquerors allmänna beteende",
        "Description[tr]": "Genel Konqueror davranışını yapılandırın",
        "Description[uk]": "Налаштувати загальну поведінку Konqueror",
        "Description[x-test]": "xxConfigure general Konqueror behaviorxx",
        "Icon": "konqueror",
        "Name": "General",
        "Name[ca]": "General",
        "Name[es]": "General",
        "Name[eu]": "Orokorra",
        "Name[nl]": "Algemeen",
        "Name[sv]": "Allmänt",
        "Name[tr]": "Genel",
        "Name[uk]": "Загальне",
        "Name[x-test]": "xxGeneralxx",
        "ServiceTypes": [
            "KCModule"
        ]
    },
    "X-DocPath": "kcontrol5/khtml-general/index.html",
    "X-KDE-Keywords": "konqueror,tabs",
    "X-KDE-Keywords[bg]": "подпрозорци,konqueror,tabs",
    "X-KDE-Keywords[bs]": "konqueror,tabs",
    "X-KDE-Keywords[ca@valencia]": "konqueror,pestanyes",
    "X-KDE-Keywords[ca]": "konqueror,pestanyes",
    "X-KDE-Keywords[cs]": "konqueror,karty",
    "X-KDE-Keywords[da]": "konqueror,faneblade",
    "X-KDE-Keywords[de]": "Unterfenster",
    "X-KDE-Keywords[el]": "Konqueror,καρτέλες",
    "X-KDE-Keywords[en_GB]": "konqueror,tabs",
    "X-KDE-Keywords[eo]": "Konkeranto",
    "X-KDE-Keywords[es]": "konqueror,pestañas",
    "X-KDE-Keywords[et]": "konqueror,kaardid",
    "X-KDE-Keywords[eu]": "konqueror,fitxak",
    "X-KDE-Keywords[fi]": "konqueror,välilehdet",
    "X-KDE-Keywords[fr]": "konqueror, onglets",
    "X-KDE-Keywords[ga]": "Konqueror,cluaisíní",
    "X-KDE-Keywords[gl]": "konqueror,separadores",
    "X-KDE-Keywords[he]": "konqueror,tabs",
    "X-KDE-Keywords[hsb]": "konqueror, tabs, jězdniki",
    "X-KDE-Keywords[hu]": "konqueror,lapok",
    "X-KDE-Keywords[ia]": "konqueror,schedas",
    "X-KDE-Keywords[id]": "Konqueror,tab",
    "X-KDE-Keywords[is]": "konqueror,flipar",
    "X-KDE-Keywords[it]": "konqueror,schede",
    "X-KDE-Keywords[ka]": "konqueror,tabs",
    "X-KDE-Keywords[kk]": "konqueror,tabs",
    "X-KDE-Keywords[km]": "konqueror ផ្ទាំង",
    "X-KDE-Keywords[ko]": "konqueror,tabs,탭",
    "X-KDE-Keywords[lt]": "Konqueror,kortelės",
    "X-KDE-Keywords[lv]": "konqueror,cilnes",
    "X-KDE-Keywords[mr]": "कॉन्करर, टॅब्स",
    "X-KDE-Keywords[nb]": "konqueror,faner",
    "X-KDE-Keywords[nds]": "Konqueror,Paneels",
    "X-KDE-Keywords[nl]": "konqueror,tabbladen",
    "X-KDE-Keywords[nn]": "Konqueror,faner",
    "X-KDE-Keywords[pa]": "ਕੋਨਕਿਉਰੋਰ,ਟੈਬ",
    "X-KDE-Keywords[pl]": "konqueror,karty",
    "X-KDE-Keywords[pt]": "konqueror,páginas",
    "X-KDE-Keywords[pt_BR]": "konqueror,abas",
    "X-KDE-Keywords[ro]": "konqueror,file",
    "X-KDE-Keywords[ru]": "konqueror,tabs,вкладки",
    "X-KDE-Keywords[sk]": "konqueror,karty",
    "X-KDE-Keywords[sl]": "konqueror,zavihki",
    "X-KDE-Keywords[sr@ijekavian]": "konqueror,tabs,К‑освајач,језичци",
    "X-KDE-Keywords[sr@ijekavianlatin]": "konqueror,tabs,K‑osvajač,jezičci",
    "X-KDE-Keywords[sr@latin]": "konqueror,tabs,K‑osvajač,jezičci",
    "X-KDE-Keywords[sr]": "konqueror,tabs,К‑освајач,језичци",
    "X-KDE-Keywords[sv]": "konqueror,flikar",
    "X-KDE-Keywords[tr]": "konqueror,sekmeler",
    "X-KDE-Keywords[uk]": "konqueror,tabs,вкладка,вкладки",
    "X-KDE-Keywords[wa]": "konqueror,linwetes",
    "X-KDE-Keywords[x-test]": "xxkonquerorxx,xxtabsxx",
    "X-KDE-Keywords[zh_CN]": "标签页",
    "X-KDE-Keywords[zh_TW]": "konqueror,tabs"
}
